marimba/__init__.py
marimba/main.py
marimba/core/__init__.py
marimba/core/pipeline.py
marimba/core/cli/__init__.py
marimba/core/cli/delete.py
marimba/core/cli/new.py
marimba/core/distribution/__init__.py
marimba/core/distribution/base.py
marimba/core/distribution/dap.py
marimba/core/distribution/s3.py
marimba/core/parallel/__init__.py
marimba/core/parallel/pipeline_loader.py
marimba/core/schemas/__init__.py
marimba/core/schemas/base.py
marimba/core/schemas/darwin.py
marimba/core/schemas/generic.py
marimba/core/schemas/ifdo.py
marimba/core/utils/__init__.py
marimba/core/utils/config.py
marimba/core/utils/constants.py
marimba/core/utils/dataset.py
marimba/core/utils/hash.py
marimba/core/utils/ifdo.py
marimba/core/utils/log.py
marimba/core/utils/manifest.py
marimba/core/utils/map.py
marimba/core/utils/metadata.py
marimba/core/utils/paths.py
marimba/core/utils/prompt.py
marimba/core/utils/rich.py
marimba/core/utils/summary.py
marimba/core/wrappers/__init__.py
marimba/core/wrappers/collection.py
marimba/core/wrappers/dataset.py
marimba/core/wrappers/pipeline.py
marimba/core/wrappers/project.py
marimba/core/wrappers/target.py
marimba/lib/__init__.py
marimba/lib/concurrency.py
marimba/lib/decorators.py
marimba/lib/exif.py
marimba/lib/gps.py
marimba/lib/image.py
marimba/lib/video.py
marimba/py.typed
marimba-1.0.1.dist-info/METADATA
marimba-1.0.1.dist-info/WHEEL
marimba-1.0.1.dist-info/entry_points.txt
marimba-1.0.1.dist-info/licenses/LICENSE
marimba-1.0.1.dist-info/RECORD
