Metadata-Version: 2.4
Name: marimba
Version: 1.0.1
Summary: A Python framework for structuring, processing, packaging and distributing FAIR scientific image datasets
Project-URL: Homepage, https://github.com/csiro-fair/marimba
Project-URL: Documentation, https://github.com/csiro-fair/marimba/tree/main/docs
Project-URL: Bug Tracker, https://github.com/csiro-fair/marimba/issues
Author-email: Chris Jackett <chris.jackett@csiro.au>, Kevin Barnard <kbarnard@mbari.org>
License: CSIRO Open Source Software Licence Agreement (variation of the BSD/MIT License)
License-File: LICENSE
Classifier: Development Status :: 5 - Production/Stable
Classifier: Intended Audience :: Science/Research
Classifier: License :: OSI Approved :: BSD License
Classifier: Programming Language :: Python :: 3.10
Classifier: Topic :: Scientific/Engineering :: Image Processing
Requires-Python: ~=3.10
Requires-Dist: av<15,>=14.0.1
Requires-Dist: boto3<2,>=1.35.94
Requires-Dist: distlib<0.4,>=0.3.8
Requires-Dist: gitpython<4,>=3.1.44
Requires-Dist: ifdo<1.3,>=1.2.5
Requires-Dist: opencv-python-headless<5,>=4.7.0.72
Requires-Dist: pandas<3,>=2.2.2
Requires-Dist: piexif<2,>=1.1.3
Requires-Dist: pillow<12,>=11.1.0
Requires-Dist: pyyaml~=6.0
Requires-Dist: rich<14,>=13.3.1
Requires-Dist: staticmap<0.6,>=0.5.7
Requires-Dist: tabulate<0.10,>=0.9.0
Requires-Dist: typer<0.16,>=0.15.1
Requires-Dist: typing-extensions<5,>=4.12.2
Provides-Extra: dev
Requires-Dist: bandit<2,>=1.7.8; extra == 'dev'
Requires-Dist: black<25,>=24.4.2; extra == 'dev'
Requires-Dist: flake8-bugbear<25,>=24.4.26; extra == 'dev'
Requires-Dist: flake8-builtins<3,>=2.5.0; extra == 'dev'
Requires-Dist: flake8-comprehensions<4,>=3.14.0; extra == 'dev'
Requires-Dist: flake8<8,>=7.0.0; extra == 'dev'
Requires-Dist: hatch<2,>=1.14.1; extra == 'dev'
Requires-Dist: isort<6,>=5.13.2; extra == 'dev'
Requires-Dist: mypy<2,>=1.10.0; extra == 'dev'
Requires-Dist: pep8-naming<0.15,>=0.14.1; extra == 'dev'
Requires-Dist: pre-commit<4,>=3.5.0; extra == 'dev'
Requires-Dist: pydocstyle<7,>=6.3.0; extra == 'dev'
Requires-Dist: pylint<4,>=3.2.0; extra == 'dev'
Requires-Dist: pytest-cov<6,>=5.0.0; extra == 'dev'
Requires-Dist: pytest<8,>=7.4.2; extra == 'dev'
Requires-Dist: ruff<0.8,>=0.7.0; extra == 'dev'
Requires-Dist: twine<7,>=6.1.0; extra == 'dev'
Requires-Dist: types-pyyaml<7,>=6.0.12.20240311; extra == 'dev'
Requires-Dist: types-requests<3,>=2.32.0.20240622; extra == 'dev'
Requires-Dist: types-tabulate<0.10,>=0.9.0.20240106; extra == 'dev'
